app_scheduler/__init__.py
app_scheduler/db.py
app_scheduler/scheduler.py
app_scheduler-0.0.1.dist-info/LICENSE.txt
app_scheduler-0.0.1.dist-info/METADATA
app_scheduler-0.0.1.dist-info/WHEEL
app_scheduler-0.0.1.dist-info/top_level.txt
app_scheduler-0.0.1.dist-info/RECORD
