Metadata-Version: 2.1
Name: app-scheduler
Version: 0.0.1
Summary: add spider scheduler
Home-page: https://gitee.com/gan_jian_wen_main/scheduling-library
Author: ganjianwen
Author-email: 1727949032@qq.com
License: UNKNOWN
Platform: UNKNOWN
Classifier: Programming Language :: Python :: 3
Classifier: License :: OSI Approved :: MIT License
Classifier: Operating System :: OS Independent
Requires-Python: >=3.6
License-File: LICENSE.txt
Requires-Dist: py3db (>=0.0.18)
Requires-Dist: openpyxl
